whisperbox/__init__.py
whisperbox/main.py
whisperbox/ai/__init__.py
whisperbox/ai/ai_service.py
whisperbox/ai/process_transcript.py
whisperbox/ai/transcribe.py
whisperbox/audio/__init__.py
whisperbox/audio/audio.py
whisperbox/audio/recording_manager.py
whisperbox/core/__init__.py
whisperbox/core/config.py
whisperbox/core/migration.py
whisperbox/core/setup.py
whisperbox/profiles/meeting_summary.yaml
whisperbox/profiles/meeting_to_blogpost.yaml
whisperbox/profiles/meeting_to_tweet.yaml
whisperbox/profiles/monologue_to_keynote.yaml
whisperbox/profiles/monologue_to_linkedin.yaml
whisperbox/profiles/monologue_to_prompt.yaml
whisperbox/profiles/personal_readme.yaml
whisperbox/profiles/pitch_perfecter.yaml
whisperbox/profiles/speaking_coach.yaml
whisperbox/profiles/storyteller.yaml
whisperbox/profiles/wisdom_distillation.yaml
whisperbox/scripts/copy_to_clipboard.py
whisperbox/scripts/output_to_markdown.py
whisperbox/scripts/output_to_terminal.py
whisperbox/scripts/send_post_request.py
whisperbox/utils/__init__.py
whisperbox/utils/logger.py
whisperbox/utils/model_utils.py
whisperbox/utils/profile_executor.py
whisperbox/utils/profile_parser.py
whisperbox/utils/utils.py
whisperbox-1.0.7.dist-info/METADATA
whisperbox-1.0.7.dist-info/WHEEL
whisperbox-1.0.7.dist-info/entry_points.txt
whisperbox-1.0.7.dist-info/licenses/LICENSE
whisperbox-1.0.7.dist-info/RECORD
