Metadata-Version: 2.4
Name: whisperbox
Version: 1.0.7
Summary: WhisperBox - Record and transcribe audio with ease
Author-email: Ty Fiero <tyfierodev@gmail.com>, Mike Bird <tooluseai@gmail.com>
License: MIT
License-File: LICENSE
Classifier: License :: OSI Approved :: MIT License
Classifier: Operating System :: OS Independent
Classifier: Programming Language :: Python :: 3
Requires-Python: >=3.10
Requires-Dist: anthropic>=0.43.0
Requires-Dist: groq>=0.15.0
Requires-Dist: inquirerpy>=0.3.4
Requires-Dist: ollama>=0.4.6
Requires-Dist: openai>=1.59.7
Requires-Dist: pyaudio>=0.2.13
Requires-Dist: pydub>=0.25.1
Requires-Dist: pyperclip>=1.9.0
Requires-Dist: pyyaml>=6.0
Requires-Dist: requests>=2.32.3
Requires-Dist: rich>=13.3.0
Requires-Dist: sounddevice>=0.5.1
Requires-Dist: toga-cocoa>=0.4.8
Requires-Dist: toga>=0.4.8
